fsm_design.v
`timescale 1us/ 1us

module fsm_design (input clk, input rst, 
            output p1, p2, p3);
  
  reg p1,p2,p3;
  reg[1:0] pres_state, next_state;
  
  parameter s0 = 2'b00;
  parameter s1 = 2'b01;
  parameter s2 = 2'b10;
  
  always @(posedge clk) begin
    if(rst) begin  //synchronous reset
      pres_state <= s0;
      next_state <= s0;
      p1         <= 0;
      p2         <= 0;
      p3         <= 0;
    end
    else pres_state <= next_state;    
  end
 
  //State machine 
  always @(*) begin
    case(pres_state)
      s0: begin
            p1 = 1;
            #120;
            p1 = 0;
            next_state = s1;
          end
      s1: begin
            p2 = 1;
            #120;
            p2 = 0;
            next_state = s2;       
          end      
      s2: begin
            p3 = 1;
            wait(rst);
            p3 = 0;
            next_state = s1;        
          end                  
    endcase
  end

endmodule

tb.sv
`timescale 1us/ 1us
module tb();
  reg clk,rst;
  reg p1,p2,p3;
 
  //design module instance 
  fsm_design fsm_combo(.clk(clk),.rst(rst),.p1(p1),.p2(p2),.p3(p3));
 
  //clock generator
  initial begin
    clk = 0;
    forever #5 clk = ~clk;
  end
  
  initial begin
    $dumpfile("dump.vcd");
    $dumpvars();
  end
  
  initial begin
    rst = 1;
    #6 rst = 0;
    #500 rst = 1;
    #10 rst = 0;
    #500 rst = 1;
    #10 rst = 0;
    #500 rst = 1;
    #10 rst = 0;
    #500 $finish;
  end
endmodule

dump.vcd
$date
	Mon Sep 23 16:54:12 2019
$end

$version
	Synopsys VCS version I-2014.03-2
$end

$timescale
	1us
$end

$comment Csum: 1 b5585d287aa035cb $end


$scope module tb $end
$var reg 1 ! clk $end
$var reg 1 " rst $end
$var reg 1 # p1 $end
$var reg 1 $ p2 $end
$var reg 1 % p3 $end

$scope module fsm_combo $end
$var wire 1 ! clk $end
$var wire 1 " rst $end
$var reg 1 # p1 $end
$var reg 1 $ p2 $end
$var reg 1 % p3 $end
$var reg 2 & pres_state [1:0] $end
$var reg 2 ' next_state [1:0] $end
$upscope $end

$upscope $end

$enddefinitions $end

#0
$dumpvars
0!
x#
x$
x%
1"
bxx '
bxx &
$end
#5
1!
b00 &
b00 '
0#
0$
0%
1#
#6
0"
#10
0!
#15
1!
#20
0!
#25
1!
#30
0!
#35
1!
#40
0!
#45
1!
#50
0!
#55
1!
#60
0!
#65
1!
#70
0!
#75
1!
#80
0!
#85
1!
#90
0!
#95
1!
#100
0!
#105
1!
#110
0!
#115
1!
#120
0!
#125
0#
b01 '
1!
b01 &
1$
#130
0!
#135
1!
#140
0!
#145
1!
#150
0!
#155
1!
#160
0!
#165
1!
#170
0!
#175
1!
#180
0!
#185
1!
#190
0!
#195
1!
#200
0!
#205
1!
#210
0!
#215
1!
#220
0!
#225
1!
#230
0!
#235
1!
#240
0!
#245
0$
b10 '
1!
b10 &
1%
#250
0!
#255
1!
#260
0!
#265
1!
#270
0!
#275
1!
#280
0!
#285
1!
#290
0!
#295
1!
#300
0!
#305
1!
#310
0!
#315
1!
#320
0!
#325
1!
#330
0!
#335
1!
#340
0!
#345
1!
#350
0!
#355
1!
#360
0!
#365
1!
#370
0!
#375
1!
#380
0!
#385
1!
#390
0!
#395
1!
#400
0!
#405
1!
#410
0!
#415
1!
#420
0!
#425
1!
#430
0!
#435
1!
#440
0!
#445
1!
#450
0!
#455
1!
#460
0!
#465
1!
#470
0!
#475
1!
#480
0!
#485
1!
#490
0!
#495
1!
#500
0!
#505
1!
#506
1"
0%
b01 '
#510
0!
#515
1!
b00 &
b00 '
1#
#516
0"
#520
0!
#525
1!
#530
0!
#535
1!
#540
0!
#545
1!
#550
0!
#555
1!
#560
0!
#565
1!
#570
0!
#575
1!
#580
0!
#585
1!
#590
0!
#595
1!
#600
0!
#605
1!
#610
0!
#615
1!
#620
0!
#625
1!
#630
0!
#635
0#
b01 '
1!
b01 &
1$
#640
0!
#645
1!
#650
0!
#655
1!
#660
0!
#665
1!
#670
0!
#675
1!
#680
0!
#685
1!
#690
0!
#695
1!
#700
0!
#705
1!
#710
0!
#715
1!
#720
0!
#725
1!
#730
0!
#735
1!
#740
0!
#745
1!
#750
0!
#755
0$
b10 '
1!
b10 &
1%
